{
  "version": "2.0.0",
  "map": {
    "width": 233,
    "height": 537,
    "areas": [
        {
            "shape": "poly",
            "coords": [
                {
                    "x": 159,
                    "y": 13
                },
                {
                    "x": 221.50270270270272,
                    "y": 13
                },
                {
                    "x": 221.50270270270272,
                    "y": 44.2972972972973
                },
                {
                    "x": 159,
                    "y": 44.2972972972973
                }
            ],
            "href": "",
            "title": "o",
            "id": 32,
            "closed": true
        },
      {
        "shape": "poly",
        "coords": [
          {
            "x": 94.5,
            "y": 157.5
          },
          {
            "x": 143.0,
            "y": 157.5
          },
          {
            "x": 143.0,
            "y": 207.0
          },
          {
            "x": 94.5,
            "y": 207.0
          }
        ],
        "href": "",
        "title": "k",
        "id": 31,
        "closed": true
      },
      {
        "shape": "poly",
        "coords": [
          {
            "x": 74.6054054054054,
            "y": 130.76216216216216
          },
          {
            "x": 117.37297297297299,
            "y": 110.30810810810812
          },
          {
            "x": 163.8594594594595,
            "y": 130.76216216216216
          },
          {
            "x": 147.12432432432433,
            "y": 151.21621621621622
          },
          {
            "x": 95.05945945945946,
            "y": 152.14594594594595
          }
        ],
        "href": "",
        "title": "u",
        "id": 30,
        "closed": true
      },
      {
        "shape": "poly",
        "coords": [
          {
            "x": 44.85405405405406,
            "y": 182.82702702702704
          },
          {
            "x": 62.51891891891893,
            "y": 139.12972972972972
          },
          {
            "x": 88.55135135135136,
            "y": 160.51351351351354
          },
          {
            "x": 87.62162162162163,
            "y": 207.0
          },
          {
            "x": 66.23783783783784,
            "y": 227.45405405405407
          }
        ],
        "href": "",
        "title": "l",
        "id": 29,
        "closed": true
      },
      {
        "shape": "poly",
        "coords": [
          {
            "x": 121.09189189189189,
            "y": 255.34594594594597
          },
          {
            "x": 163.8594594594595,
            "y": 234.8918918918919
          },
          {
            "x": 141.54594594594596,
            "y": 210.71891891891894
          },
          {
            "x": 95.05945945945946,
            "y": 214.43783783783786
          },
          {
            "x": 74.6054054054054,
            "y": 233.96216216216217
          }
        ],
        "href": "",
        "title": "d",
        "id": 28,
        "closed": true
      },
      {
        "shape": "poly",
        "coords": [
          {
            "x": 148.05405405405406,
            "y": 158.65405405405406
          },
          {
            "x": 168.50810810810813,
            "y": 140.05945945945945
          },
          {
            "x": 191.75135135135136,
            "y": 183.75675675675677
          },
          {
            "x": 170.3675675675676,
            "y": 224.66486486486488
          },
          {
            "x": 150.84324324324325,
            "y": 205.14054054054054
          }
        ],
        "href": "",
        "title": "r",
        "id": 27,
        "closed": true
      },
      {
        "shape": "poly",
        "coords": [
          {
            "x": 214.0648648648649,
            "y": 195.84324324324325
          },
          {
            "x": 214.0648648648649,
            "y": 263.71351351351353
          },
          {
            "x": 153.63243243243244,
            "y": 263.71351351351353
          }
        ],
        "href": "",
        "title": "s",
        "id": 24,
        "closed": true
      },
      {
        "shape": "poly",
        "coords": [
          {
            "x": 164.78918918918922,
            "y": 101.01081081081081
          },
          {
            "x": 214.99459459459462,
            "y": 101.01081081081081
          },
          {
            "x": 211.2756756756757,
            "y": 169.81081081081084
          }
        ],
        "href": "",
        "title": "i",
        "id": 23,
        "closed": true
      },
      {
        "shape": "poly",
        "coords": [
          {
            "x": 18.821621621621624,
            "y": 100.08108108108108
          },
          {
            "x": 19.751351351351353,
            "y": 167.95135135135135
          },
          {
            "x": 79.25405405405407,
            "y": 101.01081081081081
          }
        ],
        "href": "",
        "title": "c",
        "id": 22,
        "closed": true
      },
      {
        "shape": "poly",
        "coords": [
          {
            "x": 23.47027027027027,
            "y": 192.12432432432433
          },
          {
            "x": 22.54054054054054,
            "y": 266.5027027027027
          },
          {
            "x": 82.97297297297298,
            "y": 265.572972972973
          }
        ],
        "href": "",
        "title": "b",
        "id": 21,
        "closed": true
      },
      {
        "shape": "poly",
        "coords": [
          {
            "x": 161.07027027027027,
            "y": 404.10270270270274
          },
          {
            "x": 205.69729729729733,
            "y": 404.10270270270274
          },
          {
            "x": 205.69729729729733,
            "y": 445.0108108108108
          },
          {
            "x": 161.07027027027027,
            "y": 445.0108108108108
          }
        ],
        "href": "",
        "title": "4",
        "id": 17,
        "closed": true
      },
      {
        "shape": "poly",
        "coords": [
          {
            "x": 114.5837837837838,
            "y": 404.10270270270274
          },
          {
            "x": 161.07027027027027,
            "y": 404.10270270270274
          },
          {
            "x": 161.07027027027027,
            "y": 444.0810810810811
          },
          {
            "x": 114.5837837837838,
            "y": 444.0810810810811
          }
        ],
        "href": "",
        "title": "3",
        "id": 16,
        "closed": true
      },
      {
        "shape": "poly",
        "coords": [
          {
            "x": 72.74594594594595,
            "y": 404.10270270270274
          },
          {
            "x": 114.5837837837838,
            "y": 404.10270270270274
          },
          {
            "x": 114.5837837837838,
            "y": 444.0810810810811
          },
          {
            "x": 72.74594594594595,
            "y": 444.0810810810811
          }
        ],
        "href": "",
        "title": "2",
        "id": 15,
        "closed": true
      },
      {
        "shape": "poly",
        "coords": [
          {
            "x": 27.189189189189193,
            "y": 404.10270270270274
          },
          {
            "x": 72.74594594594595,
            "y": 404.10270270270274
          },
          {
            "x": 72.74594594594595,
            "y": 442.22162162162164
          },
          {
            "x": 27.189189189189193,
            "y": 442.22162162162164
          }
        ],
        "href": "",
        "title": "1",
        "id": 14,
        "closed": true
      },
      {
        "shape": "poly",
        "coords": [
          {
            "x": 86.6918918918919,
            "y": 274.8702702702703
          },
          {
            "x": 146.1945945945946,
            "y": 274.8702702702703
          },
          {
            "x": 146.1945945945946,
            "y": 325.0756756756757
          },
          {
            "x": 86.6918918918919,
            "y": 325.0756756756757
          }
        ],
        "href": "",
        "title": "m",
        "id": 13,
        "closed": true
      },
      {
        "shape": "poly",
        "coords": [
          {
            "x": 93.2,
            "y": 343.6702702702703
          },
          {
            "x": 145.26486486486488,
            "y": 343.6702702702703
          },
          {
            "x": 145.26486486486488,
            "y": 399.4540540540541
          },
          {
            "x": 93.2,
            "y": 399.4540540540541
          }
        ],
        "href": "",
        "title": "e",
        "id": 12,
        "closed": true
      },
      {
        "shape": "poly",
        "coords": [
          {
            "x": 213.13513513513516,
            "y": 339.9513513513514
          },
          {
            "x": 151.77297297297298,
            "y": 339.9513513513514
          },
          {
            "x": 151.77297297297298,
            "y": 399.4540540540541
          },
          {
            "x": 213.13513513513516,
            "y": 399.4540540540541
          }
        ],
        "href": "",
        "title": "v",
        "id": 11,
        "closed": true
      },
      {
        "shape": "poly",
        "coords": [
          {
            "x": 152.7027027027027,
            "y": 273.94054054054055
          },
          {
            "x": 213.13513513513516,
            "y": 273.94054054054055
          },
          {
            "x": 213.13513513513516,
            "y": 339.9513513513514
          },
          {
            "x": 152.7027027027027,
            "y": 339.9513513513514
          }
        ],
        "href": "",
        "title": "^",
        "id": 10,
        "closed": true
      },
      {
        "shape": "poly",
        "coords": [
          {
            "x": 86.6918918918919,
            "y": 337.1621621621622
          },
          {
            "x": 20.681081081081082,
            "y": 337.1621621621622
          },
          {
            "x": 20.681081081081082,
            "y": 274.8702702702703
          },
          {
            "x": 86.6918918918919,
            "y": 274.8702702702703
          }
        ],
        "href": "",
        "title": "+",
        "id": 9,
        "closed": true
      },
      {
        "shape": "poly",
        "coords": [
          {
            "x": 20.681081081081082,
            "y": 337.1621621621622
          },
          {
            "x": 86.6918918918919,
            "y": 337.1621621621622
          },
          {
            "x": 86.6918918918919,
            "y": 402.2432432432433
          },
          {
            "x": 20.681081081081082,
            "y": 402.2432432432433
          }
        ],
        "href": "",
        "title": "-",
        "id": 8,
        "closed": true
      },
      {
        "shape": "poly",
        "coords": [
          {
            "x": 172.22702702702705,
            "y": 44.2972972972973
          },
          {
            "x": 221.50270270270272,
            "y": 44.2972972972973
          },
          {
            "x": 221.50270270270272,
            "y": 95.43243243243244
          },
          {
            "x": 172.22702702702705,
            "y": 95.43243243243244
          }
        ],
        "href": "",
        "title": ">",
        "id": 4,
        "closed": true
      },
      {
        "shape": "poly",
        "coords": [
          {
            "x": 119.23243243243243,
            "y": 44.2972972972973
          },
          {
            "x": 172.22702702702705,
            "y": 44.2972972972973
          },
          {
            "x": 172.22702702702705,
            "y": 93.57297297297298
          },
          {
            "x": 119.23243243243243,
            "y": 93.57297297297298
          }
        ],
        "href": "",
        "title": "p",
        "id": 3,
        "closed": true
      },
      {
        "shape": "poly",
        "coords": [
          {
            "x": 64.37837837837839,
            "y": 44.2972972972973
          },
          {
            "x": 119.23243243243243,
            "y": 44.2972972972973
          },
          {
            "x": 119.23243243243243,
            "y": 94.5027027027027
          },
          {
            "x": 64.37837837837839,
            "y": 94.5027027027027
          }
        ],
        "href": "",
        "title": "<",
        "id": 2,
        "closed": true
      },
      {
        "shape": "poly",
        "coords": [
          {
            "x": 15.102702702702704,
            "y": 44.2972972972973
          },
          {
            "x": 64.37837837837839,
            "y": 44.2972972972973
          },
          {
            "x": 64.37837837837839,
            "y": 93.57297297297298
          },
          {
            "x": 15.102702702702704,
            "y": 93.57297297297298
          }
        ],
        "href": "",
        "title": "=",
        "id": 1,
        "closed": true
      }
    ],
    "name": "buttons.png",
    "hasDefaultArea": false,
    "dArea": {
      "shape": "default",
      "coords": [],
      "href": "",
      "title": "",
      "id": 0,
      "iMap": "buttons.png",
      "isDefault": true
    },
    "lastId": 1
  }
}
